docker_services/__init__.py
docker_services/pytest_plugin.py
docker_services-0.3.2.dist-info/LICENSE
docker_services-0.3.2.dist-info/METADATA
docker_services-0.3.2.dist-info/WHEEL
docker_services-0.3.2.dist-info/entry_points.txt
docker_services-0.3.2.dist-info/top_level.txt
docker_services-0.3.2.dist-info/RECORD
