Metadata-Version: 2.1
Name: docker-services
Version: 0.3.2
Summary: Uses docker to spawn containers for services required during tests
Home-page: https://github.com/dmonroy/docker-services
Author: Darwin Monroy
Author-email: contact@darwinmonroy.com
License: UNKNOWN
Platform: UNKNOWN
Classifier: Development Status :: 4 - Beta
Classifier: Framework :: Pytest
Classifier: License :: OSI Approved :: MIT License
Classifier: Programming Language :: Python
Classifier: Programming Language :: Python :: 2
Classifier: Programming Language :: Python :: 2.7
Classifier: Programming Language :: Python :: 3
Classifier: Programming Language :: Python :: 3.4
Classifier: Programming Language :: Python :: 3.5
Classifier: Programming Language :: Python :: 3.6
Classifier: Programming Language :: Python :: 3.7
Classifier: Topic :: Software Development :: Build Tools
Requires-Dist: docker
Requires-Dist: pytest
Requires-Dist: pyyaml
